[
  {
    "OrderID": 1,
    "CustomerID": 1001,
    "OrderDate": "2023-02-28",
    "Status": "Shipped",
    "TotalAmount": 50.00
  },
  {
    "OrderID": 2,
    "CustomerID": 1002,
    "OrderDate": "2023-03-01",
    "Status": "Processing",
    "TotalAmount": 30.00
  },
  {
    "OrderID": 3,
    "CustomerID": 1003,
    "OrderDate": "2023-03-02",
    "Status": "Delivered",
    "TotalAmount": 90.00
  },
  {
    "OrderID": 4,
    "CustomerID": 1004,
    "OrderDate": "2023-03-03",
    "Status": "Canceled",
    "TotalAmount": 0.00
  },
  {
    "OrderID": 5,
    "CustomerID": 1001,
    "OrderDate": "2023-03-04",
    "Status": "Delivered",
    "TotalAmount": 25.00
  },
  {
    "OrderID": 6,
    "CustomerID": 1005,
    "OrderDate": "2023-03-05",
    "Status": "Shipped",
    "TotalAmount": 60.00
  },
  {
    "OrderID": 7,
    "CustomerID": 1006,
    "OrderDate": "2023-03-06",
    "Status": "Processing",
    "TotalAmount": 120.00
  },
  {
    "OrderID": 8,
    "CustomerID": 1007,
    "OrderDate": "2023-03-07",
    "Status": "Delivered",
    "TotalAmount": 90.00
  },
  {
    "OrderID": 9,
    "CustomerID": 1008,
    "OrderDate": "2023-03-08",
    "Status": "Shipped",
    "TotalAmount": 25.00
  },
  {
    "OrderID": 10,
    "CustomerID": 1009,
    "OrderDate": "2023-03-09",
    "Status": "Delivered",
    "TotalAmount": 150.00
  },
  {
    "OrderID": 11,
    "CustomerID": 1010,
    "OrderDate": "2023-03-10",
    "Status": "Processing",
    "TotalAmount": 50.00
  },
  {
    "OrderID": 12,
    "CustomerID": 1011,
    "OrderDate": "2023-03-11",
    "Status": "Delivered",
    "TotalAmount": 30.00
  },
  {
    "OrderID": 13,
    "CustomerID": 1012,
    "OrderDate": "2023-03-12",
    "Status": "Shipped",
    "TotalAmount": 90.00
  },
  {
    "OrderID": 14,
    "CustomerID": 1013,
    "OrderDate": "2023-03-13",
    "Status": "Processing",
    "TotalAmount": 25.00
  },
  {
    "OrderID": 15,
    "CustomerID": 1014,
    "OrderDate": "2023-03-14",
    "Status": "Delivered",
    "TotalAmount": 150.00
  },
  {
    "OrderID": 16,
    "CustomerID": 1015,
    "OrderDate": "2023-03-15",
    "Status": "Shipped",
    "TotalAmount": 60.00
  },
  {
    "OrderID": 17,
    "CustomerID": 1016,
    "OrderDate": "2023-03-16",
    "Status": "Delivered",
    "TotalAmount": 120.00
  },
  {
    "OrderID": 18,
    "CustomerID": 1017,
    "OrderDate": "2023-03-17",
    "Status": "Processing",
    "TotalAmount": 90.00
  },
  {
    "OrderID": 19,
    "CustomerID": 1018,
    "OrderDate": "2023-03-18",
    "Status": "Shipped",
    "TotalAmount": 25.00
  },
  {
    "OrderID": 20,
    "CustomerID": 1019,
    "OrderDate": "2023-03-19",
    "Status": "Delivered",
    "TotalAmount": 150.00
  },
  {
    "OrderID": 21,
    "CustomerID": 1020,
    "OrderDate": "2023-03-20",
    "Status": "Processing",
    "TotalAmount": 50.00
  },
  {
    "OrderID": 22,
    "CustomerID": 1021,
    "OrderDate": "2023-03-21",
    "Status": "Shipped",
    "TotalAmount": 30.00
  },
  {
    "OrderID": 23,
    "CustomerID": 1022,
    "OrderDate": "2023-03-22",
    "Status": "Delivered",
    "TotalAmount": 90.00
  },
  {
    "OrderID": 24,
    "CustomerID": 1023,
    "OrderDate": "2023-03-23",
    "Status": "Processing",
    "TotalAmount": 25.00
  },
  {
    "OrderID": 25,
    "CustomerID": 1024,
    "OrderDate": "2023-03-24",
    "Status": "Shipped",
    "TotalAmount": 150.00
  },
  {
    "OrderID": 26,
    "CustomerID": 1025,
    "OrderDate": "2023-03-25",
    "Status": "Delivered",
    "TotalAmount": 60.00
  },
  {
    "OrderID": 27,
    "CustomerID": 1026,
    "OrderDate": "2023-03-26",
    "Status": "Processing",
    "TotalAmount": 120.00
  },
  {
    "OrderID": 28,
    "CustomerID": 1027,
    "OrderDate": "2023-03-27",
    "Status": "Shipped",
    "TotalAmount": 90.00
  },
  {
    "OrderID": 29,
    "CustomerID": 1028,
    "OrderDate": "2023-03-28",
    "Status": "Delivered",
    "TotalAmount": 25.00
  },
  {
    "OrderID": 30,
    "CustomerID": 1029,
    "OrderDate": "2023-03-29",
    "Status": "Processing",
    "TotalAmount": 150.00
  },
  {
    "OrderID": 31,
    "CustomerID": 1030,
    "OrderDate": "2023-03-30",
    "Status": "Shipped",
    "TotalAmount": 50.00
  },
  {
    "OrderID": 32,
    "CustomerID": 1031,
    "OrderDate": "2023-03-31",
    "Status": "Delivered",
    "TotalAmount": 30.00
  },
  {
    "OrderID": 33,
    "CustomerID": 1032,
    "OrderDate": "2023-04-01",
    "Status": "Processing",
    "TotalAmount": 90.00
  },
  {
    "OrderID": 34,
    "CustomerID": 1033,
    "OrderDate": "2023-04-02",
    "Status": "Shipped",
    "TotalAmount": 25.00
  },
  {
    "OrderID": 35,
    "CustomerID": 1034,
    "OrderDate": "2023-04-03",
    "Status": "Delivered",
    "TotalAmount": 150.00
  },
  {
    "OrderID": 36,
    "CustomerID": 1035,
    "OrderDate": "2023-04-04",
    "Status": "Processing",
    "TotalAmount": 60.00
  },
  {
    "OrderID": 37,
    "CustomerID": 1036,
    "OrderDate": "2023-04-05",
    "Status": "Shipped",
    "TotalAmount": 120.00
  },
  {
    "OrderID": 38,
    "CustomerID": 1037,
    "OrderDate": "2023-04-06",
    "Status": "Delivered",
    "TotalAmount": 90.00
  },
  {
    "OrderID": 39,
    "CustomerID": 1038,
    "OrderDate": "2023-04-07",
    "Status": "Processing",
    "TotalAmount": 25.00
  },
  {
    "OrderID": 40,
    "CustomerID": 1039,
    "OrderDate": "2023-04-08",
    "Status": "Shipped",
    "TotalAmount": 150.00
  }
]
